dempster_shafer/__init__.py
dempster_shafer/fod.py
dempster_shafer/fs.py
dempster_shafer/lattice.py
dempster_shafer/prueba.py
dempster_shafer-0.0.23.dist-info/LICENSE
dempster_shafer-0.0.23.dist-info/METADATA
dempster_shafer-0.0.23.dist-info/WHEEL
dempster_shafer-0.0.23.dist-info/top_level.txt
dempster_shafer-0.0.23.dist-info/RECORD
